WeixinXiaoChengxuJiaochengWaiBowang/README.md
WeixinXiaoChengxuJiaochengWaiBowang/__init__.py
WeixinXiaoChengxuJiaochengWaiBowang/__main__.py
WeixinXiaoChengxuJiaochengWaiBowang/file.epub
WeixinXiaoChengxuJiaochengWaiBowang/index.html
WeixinXiaoChengxuJiaochengWaiBowang/css/__init__.py
WeixinXiaoChengxuJiaochengWaiBowang/css/annotations.css
WeixinXiaoChengxuJiaochengWaiBowang/css/main.css
WeixinXiaoChengxuJiaochengWaiBowang/css/normalize.css
WeixinXiaoChengxuJiaochengWaiBowang/css/popup.css
WeixinXiaoChengxuJiaochengWaiBowang/font/__init__.py
WeixinXiaoChengxuJiaochengWaiBowang/font/fontello.eot
WeixinXiaoChengxuJiaochengWaiBowang/font/fontello.svg
WeixinXiaoChengxuJiaochengWaiBowang/font/fontello.ttf
WeixinXiaoChengxuJiaochengWaiBowang/font/fontello.woff
WeixinXiaoChengxuJiaochengWaiBowang/img/__init__.py
WeixinXiaoChengxuJiaochengWaiBowang/img/annotator-glyph-sprite.png
WeixinXiaoChengxuJiaochengWaiBowang/img/annotator-icon-sprite.png
WeixinXiaoChengxuJiaochengWaiBowang/img/apple-touch-icon.png
WeixinXiaoChengxuJiaochengWaiBowang/img/cancelfullscreen.png
WeixinXiaoChengxuJiaochengWaiBowang/img/close.png
WeixinXiaoChengxuJiaochengWaiBowang/img/fullscreen.png
WeixinXiaoChengxuJiaochengWaiBowang/img/loader.gif
WeixinXiaoChengxuJiaochengWaiBowang/img/menu-icon.png
WeixinXiaoChengxuJiaochengWaiBowang/img/save.png
WeixinXiaoChengxuJiaochengWaiBowang/img/saved.png
WeixinXiaoChengxuJiaochengWaiBowang/img/settings-s.png
WeixinXiaoChengxuJiaochengWaiBowang/img/settings.png
WeixinXiaoChengxuJiaochengWaiBowang/img/star.png
WeixinXiaoChengxuJiaochengWaiBowang/js/__init__.py
WeixinXiaoChengxuJiaochengWaiBowang/js/epub.js
WeixinXiaoChengxuJiaochengWaiBowang/js/epub.min.js
WeixinXiaoChengxuJiaochengWaiBowang/js/epub.min.map
WeixinXiaoChengxuJiaochengWaiBowang/js/hooks.min.js
WeixinXiaoChengxuJiaochengWaiBowang/js/hooks.min.map
WeixinXiaoChengxuJiaochengWaiBowang/js/reader.js
WeixinXiaoChengxuJiaochengWaiBowang/js/reader.js.map
WeixinXiaoChengxuJiaochengWaiBowang/js/reader.min.js
weixin_xiao_chengxu_jiaocheng_wai_bowang-2024.3.3.0.dist-info/METADATA
weixin_xiao_chengxu_jiaocheng_wai_bowang-2024.3.3.0.dist-info/WHEEL
weixin_xiao_chengxu_jiaocheng_wai_bowang-2024.3.3.0.dist-info/entry_points.txt
weixin_xiao_chengxu_jiaocheng_wai_bowang-2024.3.3.0.dist-info/top_level.txt
weixin_xiao_chengxu_jiaocheng_wai_bowang-2024.3.3.0.dist-info/RECORD
